game_ai_arena_sdk/.gitignore
game_ai_arena_sdk/PKG-INFO
game_ai_arena_sdk/README.md
game_ai_arena_sdk/__init__.py
game_ai_arena_sdk/bot.py
game_ai_arena_sdk/client.py
game_ai_arena_sdk/pyproject.toml
game_ai_arena_sdk/types.py
game_ai_arena_sdk/examples/__init__.py
game_ai_arena_sdk/examples/random_bot.py
game_ai_arena_sdk-0.2.2.dist-info/METADATA
game_ai_arena_sdk-0.2.2.dist-info/WHEEL
game_ai_arena_sdk-0.2.2.dist-info/RECORD
