Metadata-Version: 2.4
Name: game-ai-arena-sdk
Version: 0.2.2
Summary: Python SDK for running bots on Game AI Arena
Requires-Python: >=3.11
Requires-Dist: pydantic>=2.0
Requires-Dist: websockets>=12.0
